find_galaxies/__init__.py
find_galaxies/galaxy_classifier.py
galaxy_recognition_pipeline-0.0.1.dist-info/METADATA
galaxy_recognition_pipeline-0.0.1.dist-info/WHEEL
galaxy_recognition_pipeline-0.0.1.dist-info/top_level.txt
galaxy_recognition_pipeline-0.0.1.dist-info/RECORD
