Metadata-Version: 2.4
Name: galaxy_recognition_pipeline
Version: 0.0.1
Requires-Dist: numpy
Requires-Dist: pandas
Requires-Dist: astroquery
Requires-Dist: astropy
Requires-Dist: tqdm
Requires-Dist: matplotlib
Requires-Dist: tensorflow
Requires-Dist: pandas
Requires-Dist: scikit-learn
